[
	{
		"name": "Dominion of Neravia",
		"leaderName": "Lady Neravia",
		"adjective": "Engineers",
		"outerColor": [140,30,20],
		"innerColor": [255,70,70],
		
		"startBias": ["Coast"],
		"preferredVictoryType": "Domination",
		"favouredReligion": "Christianity",
		
		"startIntroPart1": "It has begun.",
		"startIntroPart2": "All great minds kneel of our Dominion before thee,are you ready to rule the world?",
		"startIntroPart3": "(This civ is WIP, also my very first but please have fun playing it （＾ｖ＾）) -by Neravya",
		"declaringWar": "I'll please be striking first.",
		"attacked": "Oh.. That's not convenient..",
		"defeated": "You're a great opponent, Although I'll be annoying you in afterlife for this.",
		"introduction": "Oh, well I typically consider meeting new civs a bad news, I please hope that's not your case..",
		
		"neutralHello": "Please state your intentions.",
                "hateHello": "..?",
		
		"afterPeace": "Okay.. I guess we can take a break..",
		"tradeRequest": "Mind you please consider this trade?",

                "uniqueName": "War Climate",
                "uniques": ["[+5 Production] [in all cities] <when at war> <after discovering [Mathematics]>",
		           "[+5 Production] [in all cities] <when at war> <after discovering [Physics]>",
			   "[+5 Production] [in all cities] <when at war> <after discovering [Chemistry]>",
		           "[+5 Production] [in all cities] <when at war> <after discovering [Dynamite]>",
			   "[+50]% Strength [im all cities] <when defending> <after discovering [Mathemathics]>"],
		
		"cities": ["Neravia","Horizon","Fortuna","Centix","Dorex","Sentinel","Frontier","Vanguard","Arlite",
			"Monolith","Argust","Utretch","Ark","Theorn","Bismuth","Maze Citadel","Zugzwang Manufactory",
			"Draco Manufactory","Overmind","Perpetual Core"]
	}
]
